[
  {
    "id": 1,
    "entity": "September 11 attacks",
    "type": "Event",
    "surface_forms": [
      "terrorist attacks on the World Trade Center",
      "September 11",
      "that Tuesday morning of September 11",
      "September 11",
      "as a result of September 11",
      "9/11"
    ],
    "wikipedia_title": "September_11_attacks",
    "wikipedia_url": "https://en.wikipedia.org/wiki/September_11_attacks",
    "wikidata_qid": "Q10806",
    "aliases": [
      "September 11",
      "11 September",
      "11 September 2001",
      "September 11, 2001",
      "9/11",
      "911",
      "11 September Attacks",
      "September 11th Attacks",
      "9/11 Attacks",
      "September 11, 2001 terrorist attacks"
    ],
    "description": "2001 attacks in the United States",
    "description_wiki": "The September 11 attacks, colloquially known as 9/11, were a coordinated series of suicide attacks perpetrated by the Islamist terrorist organization al-Qaeda against the United States in 2001."
  },
  {
    "id": 2,
    "entity": "World Trade Center",
    "type": "Place",
    "surface_forms": [
      "World Trade Center",
      "the World Trade Center"
    ],
    "wikipedia_title": "World_Trade_Center_(1973–2001)",
    "wikipedia_url": "https://en.wikipedia.org/wiki/World_Trade_Center_(1973–2001)",
    "wikidata_qid": "Q11235",
    "aliases": [
      "WTC",
      "Original World Trade Center",
      "World Trade Center (1973–2001)"
    ],
    "description": "former skyscraper complex in Manhattan, New York (1968-2001)",
    "description_wiki": "The original World Trade Center (WTC) was a complex of seven buildings in the Financial District of Lower Manhattan in New York City."
  },
  {
    "id": 3,
    "entity": "World Bank",
    "type": "Organization",
    "surface_forms": [
      "World Bank",
      "World Bank/International Monetary Fund"
    ],
    "wikipedia_title": "World_Bank",
    "wikipedia_url": "https://en.wikipedia.org/wiki/World_Bank",
    "wikidata_qid": "Q7164",
    "aliases": [
      "World Bank, WB",
      "The World Bank",
      "WB"
    ],
    "description": "international financial institution",
    "description_wiki": ""
  },
  {
    "id": 4,
    "entity": "International Monetary Fund",
    "type": "Organization",
    "surface_forms": [
      "International Monetary Fund",
      "World Bank/International Monetary Fund",
      "IMF"
    ],
    "wikipedia_title": "International_Monetary_Fund",
    "wikipedia_url": "https://en.wikipedia.org/wiki/International_Monetary_Fund",
    "wikidata_qid": "Q7804",
    "aliases": [
      "IMF",
      "International Monetary Fund, IMF"
    ],
    "description": "international financial institution",
    "description_wiki": "The International Monetary Fund (IMF) is an international financial institution and a specialized agency of the United Nations, headquartered in Washington, D.C. It consists of 191 member countries, and its stated mission is \"working to foster global monetary cooperation, secure financial stability, facilitate international trade, promote high employment and sustainable economic growth, and reduce poverty around the world\"."
  },
  {
    "id": 5,
    "entity": "Washington, D.C.",
    "type": "Place",
    "surface_forms": [
      "Washington, D.C.",
      "Washington",
      "D.C."
    ],
    "wikipedia_title": "Washington,_D.C.",
    "wikipedia_url": "https://en.wikipedia.org/wiki/Washington,_D.C.",
    "wikidata_qid": "Q61",
    "aliases": [
      "Washington, District of Columbia",
      "D.C. Washington",
      "The District",
      "District of Columbia",
      "City of Washington, D.C.",
      "Washington City, D.C.",
      "Nation's Capital (D.C.)",
      "Federal City (D.C.)",
      "Columbia District"
    ],
    "description": "capital city of the United States of America",
    "description_wiki": "Washington, D.C., officially the District of Columbia and commonly known as simply Washington or D.C., is the capital city and federal district of the United States."
  },
  {
    "id": 6,
    "entity": "Anacostia Park",
    "type": "Place",
    "surface_forms": [
      "Anacostia Park"
    ],
    "wikipedia_title": "Anacostia_Park",
    "wikipedia_url": "https://en.wikipedia.org/wiki/Anacostia_Park",
    "wikidata_qid": "Q4750717",
    "aliases": [],
    "description": "park in Washington, D.C., United States",
    "description_wiki": "Anacostia Park is operated by the United States National Park Service."
  },
  {
    "id": 7,
    "entity": "Statue of Liberty",
    "type": "Place",
    "surface_forms": [
      "Statue of Liberty",
      "the Statue of Liberty"
    ],
    "wikipedia_title": "Statue_of_Liberty",
    "wikipedia_url": "https://en.wikipedia.org/wiki/Statue_of_Liberty",
    "wikidata_qid": "Q9202",
    "aliases": [
      "Liberty Enlightening the World",
      "La Liberté éclairant le monde",
      "The Statue of Liberty Enlightening the World",
      "La Liberte eclairant la monde"
    ],
    "description": "American icon in New York, United States",
    "description_wiki": "The Statue of Liberty (Liberty Enlightening the World; French: La Liberté éclairant le monde) is a colossal neoclassical sculpture of a robed and crowned woman on Liberty Island in New York Harbor, within New York City."
  },
  {
    "id": 8,
    "entity": "Federal Hall National Memorial",
    "type": "Place",
    "surface_forms": [
      "Federal Hall",
      "a national park area called Federal Hall"
    ],
    "wikipedia_title": "Federal_Hall_National_Memorial",
    "wikipedia_url": "",
    "wikidata_qid": "Q858689",
    "aliases": [
      "Federal Hall National Memorial",
      "FEHA"
    ],
    "description": "building and historic site in New York City",
    "description_wiki": ""
  },
  {
    "id": 9,
    "entity": "Manhattan",
    "type": "Place",
    "surface_forms": [
      "Manhattan"
    ],
    "wikipedia_title": "Manhattan",
    "wikipedia_url": "https://en.wikipedia.org/wiki/Manhattan",
    "wikidata_qid": "Q11299",
    "aliases": [
      "Manhattan, New York City",
      "Manhattan, New York",
      "Manhattan borough, New York City",
      "Borough of Manhattan",
      "Mannahatta",
      "New York County",
      "New York County, NY",
      "New York County, New York",
      "Manhattan, NY"
    ],
    "description": "borough of New York City, New York, United States",
    "description_wiki": "Manhattan is the most densely populated and geographically smallest of the five boroughs of New York City."
  },
  {
    "id": 10,
    "entity": "Ellis Island",
    "type": "Place",
    "surface_forms": [
      "Ellis Island"
    ],
    "wikipedia_title": "Ellis_Island",
    "wikipedia_url": "https://en.wikipedia.org/wiki/Ellis_Island",
    "wikidata_qid": "Q202175",
    "aliases": [
      "Ellis Island National Monument",
      "Fort Gibson",
      "Anderson's Island",
      "Bucking Island",
      "Dyre Island",
      "Ellis' Island",
      "Ellis's Island",
      "Gibbet Island",
      "Gull Island",
      "Ki-oshk"
    ],
    "description": "island in New York Harbor in the United States of America",
    "description_wiki": "Ellis Island is an island in New York Harbor, within the U.S. states of New Jersey and New York."
  },
  {
    "id": 11,
    "entity": "Pentagon",
    "type": "Place",
    "surface_forms": [
      "Pentagon",
      "the Pentagon"
    ],
    "wikipedia_title": "The_Pentagon",
    "wikipedia_url": "https://en.wikipedia.org/wiki/The_Pentagon",
    "wikidata_qid": "Q11208",
    "aliases": [
      "Pentagon",
      "Headquarters of the United States Department of Defense",
      "Pentagon Office Building Complex",
      "Headquarters of the United States Department of War (2025–present)",
      "Headquarters of the United States Department of Defense (1947–2025)",
      "Headquarters of the United States Department of War (1789–1947)"
    ],
    "description": "headquarters of the United States Department of Defense; named after the shape of the building, a polygon with five (greek: penta) sides",
    "description_wiki": "The Pentagon is the headquarters of the United States Department of Defense, in Arlington County, Virginia, across the Potomac River from Washington, D.C. The building was constructed on an accelerated schedule during World War II. As a symbol of the U.S. military, the phrase The Pentagon is often used as a metonym for the Department of Defense and its leadership."
  },
  {
    "id": 12,
    "entity": "United States Park Police",
    "type": "Organization",
    "surface_forms": [
      "Park Police",
      "U.S. Park Police",
      "United States Park Police"
    ],
    "wikipedia_title": "United_States_Park_Police",
    "wikipedia_url": "https://en.wikipedia.org/wiki/United_States_Park_Police",
    "wikidata_qid": "Q2005254",
    "aliases": [
      "The United States Park Police"
    ],
    "description": "uniformed federal law enforcement agency",
    "description_wiki": "The United States Park Police (USPP) is the oldest uniformed federal law enforcement agency in the United States."
  },
  {
    "id": 13,
    "entity": "Carlstrom",
    "type": "Person",
    "surface_forms": [
      "Mr. Carlstrom",
      "Carlstrom"
    ],
    "wikipedia_title": "Carlstrom",
    "wikipedia_url": "",
    "wikidata_qid": "Q5042936",
    "aliases": [],
    "description": "family name",
    "description_wiki": ""
  },
  {
    "id": 14,
    "entity": "National Capital Region",
    "type": "Place",
    "surface_forms": [
      "National Capital Region",
      "regional director for the National Capital Region"
    ],
    "wikipedia_title": "National_Capital_Region",
    "wikipedia_url": "",
    "wikidata_qid": "Q13580",
    "aliases": [
      "Metropolitan Manila",
      "National Capital Region",
      "NCR"
    ],
    "description": "metropolitan area and region of the Philippines",
    "description_wiki": ""
  },
  {
    "id": 15,
    "entity": "Memorial Bridge",
    "type": "Place",
    "surface_forms": [
      "Memorial Bridge"
    ],
    "wikipedia_title": "Arlington_Memorial_Bridge",
    "wikipedia_url": "https://en.wikipedia.org/wiki/Arlington_Memorial_Bridge",
    "wikidata_qid": "Q1328779",
    "aliases": [
      "Memorial Bridge"
    ],
    "description": "bridge connecting Washington, D.C., and Arlington, Virginia",
    "description_wiki": "The Arlington Memorial Bridge (often shortened to Memorial Bridge) is a Neoclassical masonry, steel, and stone arch bridge that crosses the Potomac River in Washington, D.C., the capital of the United States."
  },
  {
    "id": 16,
    "entity": "Rock Creek Parkway",
    "type": "Place",
    "surface_forms": [
      "Rock Creek Parkway"
    ],
    "wikipedia_title": "Rock_Creek_Parkway",
    "wikipedia_url": "",
    "wikidata_qid": "Q718295",
    "aliases": [
      "Rock Creek Parkway",
      "Rock Creek and Potomac Parkway Historic District"
    ],
    "description": "parkway in Washington D.C.",
    "description_wiki": ""
  },
  {
    "id": 17,
    "entity": "Secretary of the Interior (United States)",
    "type": "Person",
    "surface_forms": [
      "Secretary of the Interior",
      "the Secretary of the Interior"
    ],
    "wikipedia_title": "United_States_Secretary_of_the_Interior",
    "wikipedia_url": "https://en.wikipedia.org/wiki/United_States_Secretary_of_the_Interior",
    "wikidata_qid": "Q2287650",
    "aliases": [
      "Secretary of the Interior"
    ],
    "description": "head of the Department of the Interior in the United States government",
    "description_wiki": "The United States secretary of the interior is the head of the United States Department of the Interior."
  },
  {
    "id": 18,
    "entity": "United States Secret Service",
    "type": "Organization",
    "surface_forms": [
      "U.S. Secret Service",
      "Secret Service",
      "the Secret Service"
    ],
    "wikipedia_title": "United_States_Secret_Service",
    "wikipedia_url": "https://en.wikipedia.org/wiki/United_States_Secret_Service",
    "wikidata_qid": "Q503224",
    "aliases": [
      "USSS",
      "US Secret Service",
      "U.S. Secret Service",
      "Secret Service"
    ],
    "description": "U.S. federal law enforcement agency",
    "description_wiki": "The United States Secret Service (USSS or Secret Service) is a federal law enforcement agency under the United States Department of Homeland Security."
  },
  {
    "id": 19,
    "entity": "United States Department of the Interior",
    "type": "Organization",
    "surface_forms": [
      "Secretary of the Interior and her staff",
      "Secretary of the Interior"
    ],
    "wikipedia_title": "United_States_Department_of_the_Interior",
    "wikipedia_url": "https://en.wikipedia.org/wiki/United_States_Department_of_the_Interior",
    "wikidata_qid": "Q608427",
    "aliases": [
      "DOI",
      "Department of the Interior",
      "US Department of the Interior",
      "Interior",
      "Interior Department",
      "U.S. Department of the Interior",
      "United States Department of Interior"
    ],
    "description": "U.S. federal executive department",
    "description_wiki": "The United States Department of the Interior (DOI) is an executive department of the U.S. federal government responsible for the management and conservation of most federal lands and natural resources."
  },
  {
    "id": 20,
    "entity": "Octagon (continuity of government plan)",
    "type": "Event",
    "surface_forms": [
      "Octagon"
    ],
    "wikipedia_title": "Continuity_of_government_in_the_United_States#Octagon",
    "wikipedia_url": "https://en.wikipedia.org/wiki/Continuity_of_government_in_the_United_States#Octagon"
  },
  {
    "id": 21,
    "entity": "White House",
    "type": "Place",
    "surface_forms": [
      "White House",
      "the White House"
    ],
    "wikipedia_title": "White_House",
    "wikipedia_url": "https://en.wikipedia.org/wiki/White_House",
    "wikidata_qid": "Q35525",
    "aliases": [
      "Executive Mansion",
      "President's Palace",
      "Presidential Mansion",
      "President's House",
      "the White House",
      "1600 Pennsylvania Avenue"
    ],
    "description": "official residence and office of the President of the United States",
    "description_wiki": "The White House is the official residence and workplace of the President of the United States."
  },
  {
    "id": 22,
    "entity": "D.C. Metropolitan Police Department",
    "type": "Organization",
    "surface_forms": [
      "D.C. Metropolitan Police",
      "Metropolitan Police",
      "Metropolitan Police Department"
    ],
    "wikipedia_title": "Metropolitan_Police_Department_of_the_District_of_Columbia",
    "wikipedia_url": "https://en.wikipedia.org/wiki/Metropolitan_Police_Department_of_the_District_of_Columbia",
    "wikidata_qid": "Q1350854",
    "aliases": [
      "MPD",
      "MPDC",
      "Metropolitan Police Department",
      "District of Columbia Police Department",
      "D.C. police department",
      "Washington, D.C. police department"
    ],
    "description": "law enforcement agency in Washington, D.C., United States",
    "description_wiki": "The Metropolitan Police Department of the District of Columbia (MPDC), more commonly known locally as the Metropolitan Police Department (MPD), and, colloquially, DC Police, is the primary law enforcement agency for the District of Columbia, in the United States."
  },
  {
    "id": 23,
    "entity": "FBI",
    "type": "Organization",
    "surface_forms": [
      "FBI"
    ],
    "wikipedia_title": "Federal_Bureau_of_Investigation",
    "wikipedia_url": "https://en.wikipedia.org/wiki/Federal_Bureau_of_Investigation",
    "wikidata_qid": "Q8333",
    "aliases": [],
    "description": "U.S. federal law enforcement agency",
    "description_wiki": "The Federal Bureau of Investigation (FBI) is the domestic intelligence and security service of the United States and its principal federal law enforcement agency."
  },
  {
    "id": 24,
    "entity": "Mayor of Washington, D.C.",
    "type": "Person",
    "surface_forms": [
      "the Mayor's office"
    ],
    "wikipedia_title": "Mayor_of_Washington,_D.C.",
    "wikipedia_url": "",
    "wikidata_qid": "Q5190572",
    "aliases": [
      "Mayor of Washington, D.C."
    ],
    "description": "head of the executive branch of the government of the District of Columbia, in the United States",
    "description_wiki": ""
  },
  {
    "id": 25,
    "entity": "Lincoln Memorial",
    "type": "Place",
    "surface_forms": [
      "Lincoln Memorial",
      "the Lincoln Memorial"
    ],
    "wikipedia_title": "Lincoln_Memorial",
    "wikipedia_url": "https://en.wikipedia.org/wiki/Lincoln_Memorial",
    "wikidata_qid": "Q213559",
    "aliases": [
      "LINC"
    ],
    "description": "memorial in Washington, D.C., United States",
    "description_wiki": "The Lincoln Memorial is  a U.S. national memorial honoring Abraham Lincoln, the 16th president of the United States, located on the western end of the National Mall of Washington, D.C. The memorial is built in a neoclassical style in the form of a classical temple."
  },
  {
    "id": 26,
    "entity": "Federal Emergency Management Agency",
    "type": "Organization",
    "surface_forms": [
      "FEMA",
      "a FEMA command post"
    ],
    "wikipedia_title": "Federal_Emergency_Management_Agency",
    "wikipedia_url": "https://en.wikipedia.org/wiki/Federal_Emergency_Management_Agency",
    "wikidata_qid": "Q503010",
    "aliases": [
      "FEMA",
      "U.S. FEMA",
      "United States Federal Emergency Management Agency"
    ],
    "description": "United States disaster response agency, part of Department of Homeland Security",
    "description_wiki": "The Federal Emergency Management Agency (FEMA) is an agency of the United States Department of Homeland Security (DHS), initially created under President Jimmy Carter by Presidential Reorganization Plan No."
  },
  {
    "id": 27,
    "entity": "Arlington County, Virginia",
    "type": "Place",
    "surface_forms": [
      "Arlington"
    ],
    "wikipedia_title": "Arlington_County,_Virginia",
    "wikipedia_url": "https://en.wikipedia.org/wiki/Arlington_County,_Virginia",
    "wikidata_qid": "Q107126",
    "aliases": [
      "Arlington County, Virginia",
      "Arlington, Virginia",
      "Arlington",
      "Arlington, VA",
      "Arlington County, VA"
    ],
    "description": "county in Virginia, United States; part of Washington metropolitan area",
    "description_wiki": "Arlington County, or simply Arlington, is a county in the U.S. state of Virginia."
  },
  {
    "id": 28,
    "entity": "Alexandria, Virginia",
    "type": "Place",
    "surface_forms": [
      "Alexandria"
    ],
    "wikipedia_title": "Alexandria,_Virginia",
    "wikipedia_url": "https://en.wikipedia.org/wiki/Alexandria,_Virginia",
    "wikidata_qid": "Q88",
    "aliases": [
      "Alexandria, Virginia",
      "City of Alexandria",
      "City of Alexandria, Virginia",
      "Alexandria, VA"
    ],
    "description": "city in the state of Virginia, United States",
    "description_wiki": "Alexandria is an independent city in the U.S. state of Virginia."
  },
  {
    "id": 29,
    "entity": "Fairfax County, Virginia",
    "type": "Place",
    "surface_forms": [
      "Fairfax County"
    ],
    "wikipedia_title": "Fairfax_County,_Virginia",
    "wikipedia_url": "https://en.wikipedia.org/wiki/Fairfax_County,_Virginia",
    "wikidata_qid": "Q341915",
    "aliases": [
      "Fairfax County, Virginia",
      "Fairfax",
      "Fairfax, Virginia",
      "Fairfax County, VA"
    ],
    "description": "county in Virginia, United States",
    "description_wiki": "Fairfax County, officially the County of Fairfax, is a county in the Commonwealth of Virginia."
  }
]