[
  {
    "id": 1,
    "entity": "Ethiopia",
    "type": "Place",
    "surface_forms": [
      "Ethiopia"
    ],
    "wikipedia_title": "Ethiopia",
    "wikipedia_url": "https://en.wikipedia.org/wiki/Ethiopia",
    "wikidata_qid": "Q115",
    "aliases": [
      "Federal Democratic Republic of Ethiopia",
      "et"
    ],
    "description": "country in the Horn of Africa",
    "description_wiki": "Ethiopia, officially the Federal Democratic Republic of Ethiopia, is a landlocked country located in the Horn of Africa region of East Africa."
  },
  {
    "id": 2,
    "entity": "Kenya",
    "type": "Place",
    "surface_forms": [
      "Kenya"
    ],
    "wikipedia_title": "Kenya",
    "wikipedia_url": "https://en.wikipedia.org/wiki/Kenya",
    "wikidata_qid": "Q114",
    "aliases": [
      "Republic of Kenya",
      "KE",
      "KEN",
      "ke"
    ],
    "description": "country in Eastern Africa",
    "description_wiki": "Kenya, officially the Republic of Kenya, is a country located in East Africa."
  },
  {
    "id": 3,
    "entity": "Minnesota",
    "type": "Place",
    "surface_forms": [
      "Minnesota"
    ],
    "wikipedia_title": "Minnesota",
    "wikipedia_url": "https://en.wikipedia.org/wiki/Minnesota",
    "wikidata_qid": "Q1527",
    "aliases": [
      "MN",
      "Land of 10,000 Lakes",
      "Minnesota, United States",
      "State of Minnesota",
      "Minn.",
      "US-MN",
      "North Star State"
    ],
    "description": "state of the United States of America",
    "description_wiki": "Minnesota is a state in the Upper Midwestern region of the United States."
  },
  {
    "id": 4,
    "entity": "University of Minnesota",
    "type": "Organization",
    "surface_forms": [
      "University of Minnesota-Twin Cities"
    ],
    "wikipedia_title": "University_of_Minnesota",
    "wikipedia_url": "https://en.wikipedia.org/wiki/University_of_Minnesota",
    "wikidata_qid": "Q238101",
    "aliases": [
      "University of Minnesota, Twin Cities",
      "University of Minnesota-Twin Cities",
      "U of M",
      "UMN",
      "The University of Minnesota, TwinCities",
      "Minnesota State University",
      "Minn. State University",
      "State University of Minnesota",
      "U. Minn.",
      "Univ. of Minnesota"
    ],
    "description": "public research university in Minneapolis and Saint Paul, Minnesota, United States",
    "description_wiki": "The University of Minnesota Twin Cities (historically known as University of Minnesota) is a public land-grant research university in the Twin Cities of Minneapolis and Saint Paul, Minnesota, United States."
  },
  {
    "id": 5,
    "entity": "John F. Kennedy International Airport",
    "type": "Place",
    "surface_forms": [
      "JFK Airport",
      "JFK Airport in New York"
    ],
    "wikipedia_title": "John_F._Kennedy_International_Airport",
    "wikipedia_url": "https://en.wikipedia.org/wiki/John_F._Kennedy_International_Airport",
    "wikidata_qid": "Q8685",
    "aliases": [
      "KJFK",
      "JFK International Airport",
      "JFK",
      "Kennedy International",
      "New York International Airport",
      "Kennedy International Airport",
      "JFK Airport",
      "Idlewild Airport",
      "Idlewild International Airport"
    ],
    "description": "international airport in New York, United States",
    "description_wiki": "John F. Kennedy International Airport (IATA: JFK, ICAO: KJFK, FAA LID: JFK) is a major international airport serving the New York metropolitan area."
  },
  {
    "id": 6,
    "entity": "United States",
    "type": "Place",
    "surface_forms": [
      "America",
      "U.S.",
      "America society",
      "America is not ready for a black president"
    ],
    "wikipedia_title": "United_States",
    "wikipedia_url": "https://en.wikipedia.org/wiki/United_States",
    "wikidata_qid": "Q30",
    "aliases": [
      "the States",
      "the United States of America",
      "US of America",
      "the US",
      "the U.S.",
      "the US of A",
      "U.S. of America",
      "the US of America",
      "the USA",
      "the U.S.A."
    ],
    "description": "country located primarily in North America",
    "description_wiki": "The United States of America (USA), also known as the United States (U.S.) or America, is a country primarily located in North America."
  },
  {
    "id": 7,
    "entity": "Barack Obama",
    "type": "Person",
    "surface_forms": [
      "Obama",
      "Obama was running for president",
      "Obama's election"
    ],
    "wikipedia_title": "Barack_Obama",
    "wikipedia_url": "https://en.wikipedia.org/wiki/Barack_Obama",
    "wikidata_qid": "Q76",
    "aliases": [
      "POTUS 44"
    ],
    "description": "president of the United States from 2009 to 2017 (born 1961)",
    "description_wiki": "Barack Hussein Obama II (born August 4, 1961) is an American politician who served as the 44th president of the United States from 2009 to 2017."
  },
  {
    "id": 8,
    "entity": "George W. Bush",
    "type": "Person",
    "surface_forms": [
      "Bush"
    ],
    "wikipedia_title": "George_W._Bush",
    "wikipedia_url": "https://en.wikipedia.org/wiki/George_W._Bush",
    "wikidata_qid": "Q207",
    "aliases": [
      "Bush Jr.",
      "Dubya",
      "Bush 43",
      "POTUS 43"
    ],
    "description": "President of the United States from 2001 to 2009",
    "description_wiki": "George Walker Bush (born July 6, 1946) is an American politician, businessman, and former United States Air Force officer who was the 43rd president of the United States, serving from 2001 to 2009."
  }
]