[
  {
    "id": 1,
    "entity": "Clarence J. Thornton",
    "type": "Person",
    "surface_forms": [
      "Clarence J. Thornton"
    ],
    "wikipedia_title": "Clarence_Thornton",
    "wikipedia_url": "https://en.wikipedia.org/wiki/Clarence_Thornton"
  },
  {
    "id": 2,
    "entity": "San Francisco",
    "type": "Place",
    "surface_forms": [
      "San Francisco",
      "the city of San Francisco",
      "San Francisco, California"
    ],
    "wikipedia_title": "San_Francisco",
    "wikipedia_url": "https://en.wikipedia.org/wiki/San_Francisco",
    "wikidata_qid": "Q62",
    "aliases": [
      "San Francisco, California",
      "The City by the Bay",
      "SF",
      "SFO",
      "The Golden City",
      "Paris of the West",
      "Baghdad by the Bay",
      "San Francisco County",
      "San Francisco County, California",
      "San Fran"
    ],
    "description": "consolidated city and county in California, United States",
    "description_wiki": "San Francisco, officially the City and County of San Francisco, is the fourth-most populous city in California and the 17th-most populous in the United States, with a population of 826,079 in 2025."
  },
  {
    "id": 3,
    "entity": "California",
    "type": "Place",
    "surface_forms": [
      "California",
      "Merced, California",
      "Merced County, California",
      "San Francisco, California"
    ],
    "wikipedia_title": "California",
    "wikipedia_url": "https://en.wikipedia.org/wiki/California",
    "wikidata_qid": "Q99",
    "aliases": [
      "State of California",
      "The Golden State",
      "Calif.",
      "California, United States",
      "Cali.",
      "Cal.",
      "CA",
      "US-CA",
      "Golden State"
    ],
    "description": "state of the United States of America",
    "description_wiki": "California () is a state in the Western United States that lies on the Pacific Coast."
  },
  {
    "id": 4,
    "entity": "Michael Thornton",
    "type": "Person",
    "surface_forms": [
      "Michael Thornton",
      "my grandfather Michael Thornton",
      "My father, Michael Thornton"
    ],
    "wikipedia_title": "Michael_Thornton",
    "wikipedia_url": "https://en.wikipedia.org/wiki/Michael_Thornton"
  },
  {
    "id": 5,
    "entity": "County Cork",
    "type": "Place",
    "surface_forms": [
      "County Cork",
      "Cork, Ireland"
    ],
    "wikipedia_title": "County_Cork",
    "wikipedia_url": "https://en.wikipedia.org/wiki/County_Cork"
  },
  {
    "id": 6,
    "entity": "Ireland",
    "type": "Place",
    "surface_forms": [
      "Ireland",
      "born in Ireland",
      "came from Ireland"
    ],
    "wikipedia_title": "Ireland",
    "wikipedia_url": "https://en.wikipedia.org/wiki/Ireland",
    "wikidata_qid": "Q22890",
    "aliases": [
      "Airlan",
      "Irland",
      "Irlanda",
      "Irlandia",
      "Auld Sod",
      "Irlande",
      "Airlann",
      "Mikra Britannia",
      "Ireland (island)",
      "Éire"
    ],
    "description": "island in the North Atlantic Ocean",
    "description_wiki": "Ireland is an island in the North Atlantic Ocean, in Northwestern Europe."
  },
  {
    "id": 7,
    "entity": "American Civil War",
    "type": "Event",
    "surface_forms": [
      "the Civil War",
      "the end of the Civil War",
      "Northern Army"
    ],
    "wikipedia_title": "American_Civil_War",
    "wikipedia_url": "https://en.wikipedia.org/wiki/American_Civil_War",
    "wikidata_qid": "Q8676",
    "aliases": [
      "War Between the States",
      "Civil War",
      "The Civil War",
      "U.S. Civil War",
      "US Civil War",
      "United States Civil War",
      "War of the Rebellion",
      "War of Northern Aggression"
    ],
    "description": "1861–1865 civil war in the United States between the North and the South over the enslavement of African-Americans",
    "description_wiki": "The American Civil War (April 12, 1861 – May 26, 1865; also known by other names) was a civil war in the United States between the Union (\"the North\") and the Confederacy (\"the South\"), which was formed in 1861 by states that had seceded from the Union to preserve slavery in the United States, which they saw as threatened because of the election of Abraham Lincoln and the growing abolitionist movement in the North."
  },
  {
    "id": 8,
    "entity": "Ellen Hamlon Thornton",
    "type": "Person",
    "surface_forms": [
      "Ellen Hamlon Thornton",
      "my grandmother Ellen Hamlon Thornton"
    ],
    "wikipedia_title": "Ellen_Hamlon_Thornton",
    "wikipedia_url": "https://en.wikipedia.org/wiki/Ellen_Hamlon_Thornton"
  },
  {
    "id": 9,
    "entity": "Merced",
    "type": "Place",
    "surface_forms": [
      "Merced",
      "Merced, California",
      "Merced County"
    ],
    "wikipedia_title": "Merced,_California",
    "wikipedia_url": "https://en.wikipedia.org/wiki/Merced,_California",
    "wikidata_qid": "Q499189",
    "aliases": [
      "Merced, California",
      "Merced, CA"
    ],
    "description": "city in and county seat of Merced County, California, United States",
    "description_wiki": "Merced (  mur-SED; from Spanish for 'Mercy', pronounced [meɾˈseð]) is a city in and the county seat of Merced County, California, United States, in the San Joaquin Valley."
  },
  {
    "id": 10,
    "entity": "Reno, Nevada",
    "type": "Place",
    "surface_forms": [
      "Reno, Nevada",
      "Reno"
    ],
    "wikipedia_title": "Reno,_Nevada",
    "wikipedia_url": "https://en.wikipedia.org/wiki/Reno,_Nevada",
    "wikidata_qid": "Q49225",
    "aliases": [
      "Reno, Nevada",
      "Reno, NV"
    ],
    "description": "city in and county seat of Washoe County, Nevada, United States",
    "description_wiki": "Reno (, REE-noh) is a city in the northwest section of the U.S. state of Nevada, along the Nevada–California border."
  },
  {
    "id": 11,
    "entity": "Nevada",
    "type": "Place",
    "surface_forms": [
      "Nevada"
    ],
    "wikipedia_title": "Nevada",
    "wikipedia_url": "https://en.wikipedia.org/wiki/Nevada",
    "wikidata_qid": "Q1227",
    "aliases": [
      "NV",
      "State of Nevada",
      "Nevada, United States",
      "Nev.",
      "The Silver State",
      "US-NV",
      "Silver State"
    ],
    "description": "state of the United States of America",
    "description_wiki": "Nevada (  nə-VAD-ə; Spanish: [neˈβaða] ) is a landlocked state in the Western United States."
  },
  {
    "id": 12,
    "entity": "Margaret Joyce",
    "type": "Person",
    "surface_forms": [
      "Margaret Joyce",
      "Miss Margaret Joyce"
    ],
    "wikipedia_title": "Margaret_Joyce",
    "wikipedia_url": "https://en.wikipedia.org/wiki/Margaret_Joyce"
  },
  {
    "id": 13,
    "entity": "Massachusetts",
    "type": "Place",
    "surface_forms": [
      "Massachusetts"
    ],
    "wikipedia_title": "Massachusetts",
    "wikipedia_url": "https://en.wikipedia.org/wiki/Massachusetts",
    "wikidata_qid": "Q771",
    "aliases": [
      "Bay State",
      "Commonwealth of Massachusetts",
      "MA",
      "Mass.",
      "US-MA",
      "The Commonwealth of Massachusetts",
      "Massachusetts, United States",
      "State of Massachusetts",
      "The Bay State",
      "Massachusetts (U.S. state)"
    ],
    "description": "state of the United States of America",
    "description_wiki": "Massachusetts (   MASS-ə-CHOO-sits, -⁠zits; Massachusett: Muhsachuweesut [məhswatʃəwiːsət]), officially the Commonwealth of Massachusetts, is a state in the New England region of the Northeastern United States."
  },
  {
    "id": 14,
    "entity": "John William Thornton",
    "type": "Person",
    "surface_forms": [
      "John William Thornton",
      "my grandfather's brother, John William Thornton"
    ],
    "wikipedia_title": "John_William_Thornton",
    "wikipedia_url": "https://en.wikipedia.org/wiki/John_William_Thornton"
  }
]