[
  {
    "id": 1,
    "entity": "Louisburg, North Carolina",
    "type": "Place",
    "surface_forms": [
      "Louisburg",
      "the little town of Louisburg"
    ],
    "wikipedia_title": "Louisburg, North Carolina",
    "wikipedia_url": "https://en.wikipedia.org/wiki/Louisburg, North Carolina",
    "wikidata_qid": "Q2026010",
    "aliases": [
      "Louisburg, North Carolina",
      "Louisburg, NC"
    ],
    "description": "town in Franklin County, North Carolina",
    "description_wiki": "Louisburg is a town in and the county seat of Franklin County, North Carolina,  United States."
  },
  {
    "id": 2,
    "entity": "Franklin County, North Carolina",
    "type": "Place",
    "surface_forms": [
      "Franklin County"
    ],
    "wikipedia_title": "Franklin County, North Carolina",
    "wikipedia_url": "https://en.wikipedia.org/wiki/Franklin County, North Carolina",
    "wikidata_qid": "Q502526",
    "aliases": [
      "Franklin County, North Carolina",
      "Franklin County, NC"
    ],
    "description": "county in North Carolina, United States",
    "description_wiki": "Franklin County is a county located in the U.S. state of North Carolina."
  },
  {
    "id": 3,
    "entity": "Seaboard Air Line Railroad",
    "type": "Organization",
    "surface_forms": [
      "Seaboard Railroad"
    ],
    "wikipedia_title": "Seaboard_Air_Line_Railroad",
    "wikipedia_url": "https://en.wikipedia.org/wiki/Seaboard_Air_Line_Railroad",
    "wikidata_qid": "Q175292",
    "aliases": [
      "SAL"
    ],
    "description": "former American railroad (1900-1967)",
    "description_wiki": "The Seaboard Air Line Railroad (reporting mark SAL), known colloquially as the Seaboard Railroad during its time, was an American railroad that existed from April 14, 1900, until July 1, 1967, when it merged with the Atlantic Coast Line Railroad, its longtime rival, to form the Seaboard Coast Line Railroad."
  },
  {
    "id": 4,
    "entity": "Wake Forest University",
    "type": "Organization",
    "surface_forms": [
      "Wake Forest law school",
      "Wake Forest College",
      "Wake Forest"
    ],
    "wikipedia_title": "Wake_Forest_University",
    "wikipedia_url": "https://en.wikipedia.org/wiki/Wake_Forest_University",
    "wikidata_qid": "Q392667",
    "aliases": [
      "Wake Forest College",
      "WFU"
    ],
    "description": "university in Winston-Salem, North Carolina, United States",
    "description_wiki": "Wake Forest University (Wake or WFU) is a private research university in Winston-Salem, North Carolina, United States."
  },
  {
    "id": 5,
    "entity": "Raleigh, North Carolina",
    "type": "Place",
    "surface_forms": [
      "Raleigh",
      "this city"
    ],
    "wikipedia_title": "Raleigh, North Carolina",
    "wikipedia_url": "https://en.wikipedia.org/wiki/Raleigh, North Carolina",
    "wikidata_qid": "Q41087",
    "aliases": [
      "Raleigh, North Carolina",
      "Raleigh, NC",
      "Raleigh, N.C."
    ],
    "description": "city in and state capital of North Carolina, United States of America",
    "description_wiki": "Raleigh (  RAH-lee) is the capital city of the U.S. state of North Carolina."
  },
  {
    "id": 6,
    "entity": "Murphy School",
    "type": "Organization",
    "surface_forms": [
      "Murphy school"
    ],
    "wikipedia_title": "Murphy_School",
    "wikipedia_url": "",
    "wikidata_qid": "Q110025511",
    "aliases": [],
    "description": "historic place in Murphy, Collin County, Texas",
    "description_wiki": ""
  },
  {
    "id": 7,
    "entity": "Hugh Morson High School",
    "type": "Organization",
    "surface_forms": [
      "Hugh Morson",
      "Hugh Morson High School"
    ],
    "wikipedia_title": "Hugh_Morson_High_School",
    "wikipedia_url": "https://en.wikipedia.org/wiki/Hugh_Morson_High_School"
  },
  {
    "id": 8,
    "entity": "Southern Baptist Theological Seminary",
    "type": "Organization",
    "surface_forms": [
      "Southern Baptist Seminary",
      "Louisville Seminary"
    ],
    "wikipedia_title": "Southern_Baptist_Theological_Seminary",
    "wikipedia_url": "https://en.wikipedia.org/wiki/Southern_Baptist_Theological_Seminary",
    "wikidata_qid": "Q7569667",
    "aliases": [
      "SBTS",
      "Southern Seminary"
    ],
    "description": "seminary in Louisville, Kentucky",
    "description_wiki": "The Southern Baptist Theological Seminary (SBTS) is a Baptist theological institute in Louisville, Kentucky."
  },
  {
    "id": 9,
    "entity": "Pittsboro, North Carolina",
    "type": "Place",
    "surface_forms": [
      "Pittsboro"
    ],
    "wikipedia_title": "Pittsboro, North Carolina",
    "wikipedia_url": "https://en.wikipedia.org/wiki/Pittsboro, North Carolina",
    "wikidata_qid": "Q212559",
    "aliases": [
      "Pittsboro, North Carolina",
      "Pittsboro, NC"
    ],
    "description": "town in North Carolina, United States",
    "description_wiki": "Pittsboro is a town in and the county seat of Chatham County, North Carolina, United States."
  },
  {
    "id": 10,
    "entity": "Chatham County, North Carolina",
    "type": "Place",
    "surface_forms": [
      "Chatham County"
    ],
    "wikipedia_title": "Chatham County, North Carolina",
    "wikipedia_url": "https://en.wikipedia.org/wiki/Chatham County, North Carolina",
    "wikidata_qid": "Q504410",
    "aliases": [
      "Chatham County, North Carolina",
      "Chatham County, NC"
    ],
    "description": "county in North Carolina, United States",
    "description_wiki": "Chatham County (locally  CHAT-əm) is a county located in the Piedmont area of the U.S. state of North Carolina."
  },
  {
    "id": 11,
    "entity": "Randolph County, North Carolina",
    "type": "Place",
    "surface_forms": [
      "Randolph County"
    ],
    "wikipedia_title": "Randolph County, North Carolina",
    "wikipedia_url": "https://en.wikipedia.org/wiki/Randolph County, North Carolina",
    "wikidata_qid": "Q507943",
    "aliases": [
      "Randolph County, North Carolina",
      "Randolph County, NC"
    ],
    "description": "county in North Carolina, United States",
    "description_wiki": "Randolph County is a county located in the U.S. state of North Carolina."
  },
  {
    "id": 12,
    "entity": "Liberty, North Carolina",
    "type": "Place",
    "surface_forms": [
      "Liberty"
    ],
    "wikipedia_title": "Liberty, North Carolina",
    "wikipedia_url": "https://en.wikipedia.org/wiki/Liberty, North Carolina",
    "wikidata_qid": "Q583858",
    "aliases": [
      "Liberty, North Carolina",
      "Liberty, NC"
    ],
    "description": "human settlement in Randolph County, North Carolina, United States of America",
    "description_wiki": "Liberty is a town in Randolph County, North Carolina, United States."
  },
  {
    "id": 13,
    "entity": "Weldon, North Carolina",
    "type": "Place",
    "surface_forms": [
      "Weldon"
    ],
    "wikipedia_title": "Weldon, North Carolina",
    "wikipedia_url": "https://en.wikipedia.org/wiki/Weldon, North Carolina",
    "wikidata_qid": "Q2028446",
    "aliases": [
      "Weldon, North Carolina",
      "Weldon, NC"
    ],
    "description": "town in Halifax County, North Carolina, United States",
    "description_wiki": "Weldon is a town in Halifax County, North Carolina, United States."
  },
  {
    "id": 14,
    "entity": "Elizabeth City, North Carolina",
    "type": "Place",
    "surface_forms": [
      "Elizabeth City"
    ],
    "wikipedia_title": "Elizabeth City, North Carolina",
    "wikipedia_url": "https://en.wikipedia.org/wiki/Elizabeth City, North Carolina",
    "wikidata_qid": "Q1018467",
    "aliases": [
      "Elizabeth City, North Carolina",
      "Elizabeth City, NC"
    ],
    "description": "city in Pasquotank County and Camden County, North Carolina, United States",
    "description_wiki": "Elizabeth City is a city in Pasquotank county, North Carolina, United States."
  },
  {
    "id": 15,
    "entity": "First Baptist Church (Elizabeth City, North Carolina)",
    "type": "Organization",
    "surface_forms": [
      "Elizabeth City First Baptist Church"
    ],
    "wikipedia_title": "First_Baptist_Church_(Elizabeth_City,_North_Carolina)",
    "wikipedia_url": "https://en.wikipedia.org/wiki/First_Baptist_Church_(Elizabeth_City,_North_Carolina)"
  },
  {
    "id": 16,
    "entity": "Pullen Memorial Baptist Church",
    "type": "Organization",
    "surface_forms": [
      "Pullen Memorial Baptist Church",
      "Pullen Memorial"
    ],
    "wikipedia_title": "Pullen_Memorial_Baptist_Church",
    "wikipedia_url": "https://en.wikipedia.org/wiki/Pullen_Memorial_Baptist_Church",
    "wikidata_qid": "Q7259428",
    "aliases": [],
    "description": "church building in Raleigh, North Carolina, United States of America",
    "description_wiki": "Pullen Memorial Baptist Church is a progressive Baptist church located in Raleigh, North Carolina, US, right beside North Carolina State University."
  },
  {
    "id": 17,
    "entity": "Edwin McNeill Poteat",
    "type": "Person",
    "surface_forms": [
      "Dr. Edwin McNeill Poteat",
      "Edwin McNeill Poteat"
    ],
    "wikipedia_title": "Edwin_McNeill_Poteat",
    "wikipedia_url": "",
    "wikidata_qid": "Q73823070",
    "aliases": [
      "Edwin McNeill Poteat, Jr."
    ],
    "description": "born 1892; died 1955",
    "description_wiki": ""
  },
  {
    "id": 18,
    "entity": "Southern Baptist Convention",
    "type": "Organization",
    "surface_forms": [
      "Southern Baptist Convention",
      "Southern Baptist"
    ],
    "wikipedia_title": "Southern_Baptist_Convention",
    "wikipedia_url": "https://en.wikipedia.org/wiki/Southern_Baptist_Convention",
    "wikidata_qid": "Q1351880",
    "aliases": [
      "SBC",
      "Great Commission Baptists",
      "Southern Baptist Convention"
    ],
    "description": "Christian denomination",
    "description_wiki": "The Southern Baptist Convention (SBC), alternatively the Great Commission Baptists (GCB), is a Christian denomination based in the United States."
  },
  {
    "id": 19,
    "entity": "American Baptist Churches USA",
    "type": "Organization",
    "surface_forms": [
      "American Baptist Convention"
    ],
    "wikipedia_title": "American_Baptist_Churches_USA",
    "wikipedia_url": "https://en.wikipedia.org/wiki/American_Baptist_Churches_USA",
    "wikidata_qid": "Q463455",
    "aliases": [
      "Northern Baptist Convention",
      "American Baptist Convention"
    ],
    "description": "Baptist Mainline Protestant denomination in the United States",
    "description_wiki": "The American Baptist Churches USA, abbreviated as ABCUSA, is a mainline Protestant and Baptist Christian denomination in the United States of America."
  },
  {
    "id": 20,
    "entity": "Mason–Dixon line",
    "type": "Place",
    "surface_forms": [
      "Mason-Dixon line"
    ],
    "wikipedia_title": "Mason%E2%80%93Dixon_line",
    "wikipedia_url": "https://en.wikipedia.org/wiki/Mason%E2%80%93Dixon_line"
  },
  {
    "id": 21,
    "entity": "Civil War",
    "type": "Event",
    "surface_forms": [
      "Civil War"
    ],
    "wikipedia_title": "American_Civil_War",
    "wikipedia_url": "https://en.wikipedia.org/wiki/American_Civil_War",
    "wikidata_qid": "Q8676",
    "aliases": [
      "War Between the States",
      "Civil War",
      "The Civil War",
      "U.S. Civil War",
      "US Civil War",
      "United States Civil War",
      "War of the Rebellion",
      "War of Northern Aggression"
    ],
    "description": "1861–1865 civil war in the United States between the North and the South over the enslavement of African-Americans",
    "description_wiki": "The American Civil War (April 12, 1861 – May 26, 1865; also known by other names) was a civil war in the United States between the Union (\"the North\") and the Confederacy (\"the South\"), which was formed in 1861 by states that had seceded from the Union to preserve slavery in the United States, which they saw as threatened because of the election of Abraham Lincoln and the growing abolitionist movement in the North."
  },
  {
    "id": 22,
    "entity": "Order of Railroad Conductors",
    "type": "Organization",
    "surface_forms": [
      "Order of Railroad Conductors"
    ],
    "wikipedia_title": "Order_of_Railroad_Conductors",
    "wikipedia_url": "https://en.wikipedia.org/wiki/Order_of_Railroad_Conductors"
  },
  {
    "id": 23,
    "entity": "United Church of Christ",
    "type": "Organization",
    "surface_forms": [
      "United Church"
    ],
    "wikipedia_title": "United_Church_of_Christ",
    "wikipedia_url": "https://en.wikipedia.org/wiki/United_Church_of_Christ",
    "wikidata_qid": "Q426316",
    "aliases": [
      "UCC",
      "Lancaster Theological Seminary"
    ],
    "description": "Congregational and Reformed Mainline Protestant denomination in the United States",
    "description_wiki": "The United Church of Christ (UCC) is a mainline Protestant Christian denomination based in the United States."
  },
  {
    "id": 24,
    "entity": "Union Theological Seminary (New York City)",
    "type": "Organization",
    "surface_forms": [
      "Union Seminary"
    ],
    "wikipedia_title": "Union_Theological_Seminary_(New_York_City)",
    "wikipedia_url": "https://en.wikipedia.org/wiki/Union_Theological_Seminary_(New_York_City)"
  },
  {
    "id": 25,
    "entity": "Harry Ward",
    "type": "Person",
    "surface_forms": [
      "Harry Ward"
    ],
    "wikipedia_title": "Harry_Ward",
    "wikipedia_url": "https://en.wikipedia.org/wiki/Harry_Ward",
    "wikidata_qid": "Q1586863",
    "aliases": [],
    "description": "Wikimedia disambiguation page",
    "description_wiki": "Harry Ward may refer to:\n\nHarry Ward (athlete) (ca."
  },
  {
    "id": 26,
    "entity": "Reinhold Niebuhr",
    "type": "Person",
    "surface_forms": [
      "Reinhold Niebuhr"
    ],
    "wikipedia_title": "Reinhold_Niebuhr",
    "wikipedia_url": "https://en.wikipedia.org/wiki/Reinhold_Niebuhr",
    "wikidata_qid": "Q358561",
    "aliases": [
      "Karl Paul Reinhold Niebuhr"
    ],
    "description": "American Protestant theologian (1892–1971)",
    "description_wiki": "Karl Paul Reinhold Niebuhr (June 21, 1892 – June 1, 1971) was an American Reformed theologian, ethicist, commentator on politics and public affairs, and professor at Union Theological Seminary for more than 30 years."
  },
  {
    "id": 27,
    "entity": "Henry Sloane Coffin",
    "type": "Person",
    "surface_forms": [
      "Henry Sloan Coffin"
    ],
    "wikipedia_title": "Henry_Sloane_Coffin",
    "wikipedia_url": "https://en.wikipedia.org/wiki/Henry_Sloane_Coffin",
    "wikidata_qid": "Q5728400",
    "aliases": [],
    "description": "American minister (1877-1954)",
    "description_wiki": "Henry Sloane Coffin (January 5, 1877 – November 25, 1954) was president of the Union Theological Seminary, Moderator of the Presbyterian Church in the United States of America, and one of the most famous ministers in the United States."
  },
  {
    "id": 28,
    "entity": "The Progressive",
    "type": "Work",
    "surface_forms": [
      "The Progressive Magazine",
      "The Progressive"
    ],
    "wikipedia_title": "The_Progressive",
    "wikipedia_url": "https://en.wikipedia.org/wiki/The_Progressive",
    "wikidata_qid": "Q124706",
    "aliases": [
      "The Progressive Magazine",
      "progressive.org"
    ],
    "description": "American political magazine and website",
    "description_wiki": "The Progressive is a left-leaning American magazine and website covering politics and culture."
  },
  {
    "id": 29,
    "entity": "The Nation",
    "type": "Work",
    "surface_forms": [
      "The Nation"
    ],
    "wikipedia_title": "The_Nation",
    "wikipedia_url": "https://en.wikipedia.org/wiki/The_Nation",
    "wikidata_qid": "Q1897630",
    "aliases": [],
    "description": "American weekly magazine on left politics and culture",
    "description_wiki": "The Nation is a progressive American monthly magazine that covers political and cultural news, opinion, and analysis."
  },
  {
    "id": 30,
    "entity": "The New Republic",
    "type": "Work",
    "surface_forms": [
      "The New Republic"
    ],
    "wikipedia_title": "The_New_Republic",
    "wikipedia_url": "https://en.wikipedia.org/wiki/The_New_Republic",
    "wikidata_qid": "Q1329873",
    "aliases": [],
    "description": "American magazine",
    "description_wiki": "The New Republic (often abbreviated as TNR) is an American magazine focused on domestic politics, news, culture, and the arts."
  },
  {
    "id": 31,
    "entity": "The Christian Century",
    "type": "Work",
    "surface_forms": [
      "The Christian Century"
    ],
    "wikipedia_title": "The_Christian_Century",
    "wikipedia_url": "https://en.wikipedia.org/wiki/The_Christian_Century",
    "wikidata_qid": "Q1825683",
    "aliases": [
      "Christian Century"
    ],
    "description": "Christian magazine based in Chicago",
    "description_wiki": "The Christian Century is a Christian magazine based in Chicago, Illinois."
  },
  {
    "id": 32,
    "entity": "Christianity and Crisis",
    "type": "Work",
    "surface_forms": [
      "Christianity and Crisis"
    ],
    "wikipedia_title": "Christianity_and_Crisis",
    "wikipedia_url": "",
    "wikidata_qid": "Q27716917",
    "aliases": [
      "Christ Crisis"
    ],
    "description": "journal",
    "description_wiki": ""
  },
  {
    "id": 33,
    "entity": "Robert Frost",
    "type": "Person",
    "surface_forms": [
      "Robert Frost"
    ],
    "wikipedia_title": "Robert_Frost",
    "wikipedia_url": "https://en.wikipedia.org/wiki/Robert_Frost",
    "wikidata_qid": "Q168728",
    "aliases": [
      "Robert Lee Frost"
    ],
    "description": "American poet (1874–1963)",
    "description_wiki": "Robert Lee Frost (March 26, 1874 – January 29, 1963) was an American poet."
  },
  {
    "id": 34,
    "entity": "Frank Porter Graham",
    "type": "Person",
    "surface_forms": [
      "Dr. Frank Porter Graham",
      "Frank Porter Graham",
      "Frank Graham"
    ],
    "wikipedia_title": "Frank_Porter_Graham",
    "wikipedia_url": "https://en.wikipedia.org/wiki/Frank_Porter_Graham",
    "wikidata_qid": "Q5489054",
    "aliases": [],
    "description": "Historian and politician",
    "description_wiki": "Frank Porter Graham (October 14, 1886 – February 16, 1972) was an American educator and political activist."
  },
  {
    "id": 35,
    "entity": "University of North Carolina at Chapel Hill",
    "type": "Organization",
    "surface_forms": [
      "University of North Carolina",
      "UNC"
    ],
    "wikipedia_title": "University_of_North_Carolina_at_Chapel_Hill",
    "wikipedia_url": "https://en.wikipedia.org/wiki/University_of_North_Carolina_at_Chapel_Hill",
    "wikidata_qid": "Q192334",
    "aliases": [
      "University of North Carolina",
      "UNC",
      "UNC-CH",
      "UNC-Chapel Hill",
      "UNC Chapel Hill",
      "UNCCH",
      "University of North Carolina–Chapel Hill",
      "University of North Carolina at Chapel Hill for its Department of Romance Studies"
    ],
    "description": "public research university in Chapel Hill, North Carolina, United States",
    "description_wiki": "The University of North Carolina at Chapel Hill (UNC Chapel Hill, UNC, North Carolina or Carolina) is a public research university in Chapel Hill, North Carolina, United States."
  },
  {
    "id": 36,
    "entity": "Presbyterian Church (USA)",
    "type": "Organization",
    "surface_forms": [
      "Presbyterian church",
      "Presbyterians"
    ],
    "wikipedia_title": "Presbyterian_Church_(USA)",
    "wikipedia_url": "https://en.wikipedia.org/wiki/Presbyterian_Church_(USA)",
    "wikidata_qid": "Q1149100",
    "aliases": [
      "PCUSA",
      "PC (USA)",
      "Presbyterian Church in the United States",
      "United Presbyterian Church in the U.S.A."
    ],
    "description": "Mainline Protestant denomination in the United States",
    "description_wiki": "The Presbyterian Church (USA), abbreviated PCUSA, is a mainline Protestant denomination in the United States."
  },
  {
    "id": 37,
    "entity": "Charles Jones (Presbyterian minister)",
    "type": "Person",
    "surface_forms": [
      "Reverend Charles Jones",
      "Charles Jones"
    ],
    "wikipedia_title": "Charles_Jones_(Presbyterian_minister)",
    "wikipedia_url": "https://en.wikipedia.org/wiki/Charles_Jones_(Presbyterian_minister)"
  },
  {
    "id": 38,
    "entity": "Communism",
    "type": "Event",
    "surface_forms": [
      "communist infiltrated",
      "communists"
    ],
    "wikipedia_title": "Communism",
    "wikipedia_url": "https://en.wikipedia.org/wiki/Communism",
    "wikidata_qid": "Q6186",
    "aliases": [],
    "description": "political and socioeconomic ideology",
    "description_wiki": "Communism (from Latin  communis 'common, universal') is a political and economic ideology whose goal is the creation of a communist society, a socioeconomic order centered on common ownership of the means of production, distribution, and exchange that allocates products in society based on need."
  },
  {
    "id": 39,
    "entity": "Thomas Jefferson",
    "type": "Person",
    "surface_forms": [
      "Thomas Jefferson"
    ],
    "wikipedia_title": "Thomas_Jefferson",
    "wikipedia_url": "https://en.wikipedia.org/wiki/Thomas_Jefferson",
    "wikidata_qid": "Q11812",
    "aliases": [
      "President Jefferson",
      "T. Jefferson"
    ],
    "description": "president of the United States from 1801 to 1809 (1743–1826)",
    "description_wiki": "Thomas Jefferson (April 13 [O.S. April 2], 1743 – July 4, 1826) was an American Founding Father and the third president of the United States from 1801 to 1809."
  },
  {
    "id": 40,
    "entity": "Bill of Rights",
    "type": "Work",
    "surface_forms": [
      "Bill of Rights"
    ],
    "wikipedia_title": "United_States_Bill_of_Rights",
    "wikipedia_url": "https://en.wikipedia.org/wiki/United_States_Bill_of_Rights",
    "wikidata_qid": "Q862765",
    "aliases": [
      "United States Constitution 1st-10th Amendments",
      "1st-10th Amendments",
      "1 Stat. 97",
      "First Ten Amendments to U.S. Constitution",
      "US Bill of Rights",
      "U.S. Bill of Rights",
      "Bill of Rights"
    ],
    "description": "first ten amendments to the United States Constitution",
    "description_wiki": "The United States Bill of Rights comprises the first ten amendments to the United States Constitution."
  },
  {
    "id": 41,
    "entity": "North Carolina Advisory Committee to the United States Commission on Civil Rights",
    "type": "Organization",
    "surface_forms": [
      "North Carolina Advisory Committee of the U.S. Commission on Civil Rights",
      "North Carolina Advisory Committee"
    ],
    "wikipedia_title": "United_States_Commission_on_Civil_Rights",
    "wikipedia_url": "https://en.wikipedia.org/wiki/United_States_Commission_on_Civil_Rights",
    "wikidata_qid": "Q7889639",
    "aliases": [
      "Commission on Civil Rights",
      "U.S. Commission on Civil Rights",
      "USCCR",
      "CCR"
    ],
    "description": "government agency",
    "description_wiki": "The United States Commission on Civil Rights (CCR) is a bipartisan, independent commission of the United States federal government, created by the Civil Rights Act of 1957 during the Eisenhower administration, which is charged with the responsibility for investigating, reporting on, and making recommendations concerning civil rights issues in the United States."
  },
  {
    "id": 42,
    "entity": "Fayetteville Street",
    "type": "Place",
    "surface_forms": [
      "Fayetteville Street"
    ],
    "wikipedia_title": "Fayetteville_Street_(Raleigh,_North_Carolina)",
    "wikipedia_url": "https://en.wikipedia.org/wiki/Fayetteville_Street_(Raleigh,_North_Carolina)"
  },
  {
    "id": 43,
    "entity": "S&W Cafeteria",
    "type": "Organization",
    "surface_forms": [
      "S&W Cafeteria"
    ],
    "wikipedia_title": "S&W_Cafeteria",
    "wikipedia_url": "https://en.wikipedia.org/wiki/S&W_Cafeteria",
    "wikidata_qid": "Q7387010",
    "aliases": [],
    "description": "defunct restaurant chain in North Carolina",
    "description_wiki": "S&W Cafeteria was a Charlotte, North Carolina–based chain of cafeteria-style restaurants."
  },
  {
    "id": 44,
    "entity": "Shaw University",
    "type": "Organization",
    "surface_forms": [
      "Shaw University"
    ],
    "wikipedia_title": "Shaw_University",
    "wikipedia_url": "https://en.wikipedia.org/wiki/Shaw_University",
    "wikidata_qid": "Q3443493",
    "aliases": [
      "Raleigh Institute"
    ],
    "description": "American university",
    "description_wiki": "Shaw University is a private historically Black university in Raleigh, North Carolina."
  },
  {
    "id": 45,
    "entity": "NAACP",
    "type": "Organization",
    "surface_forms": [
      "NAACP"
    ],
    "wikipedia_title": "NAACP",
    "wikipedia_url": "https://en.wikipedia.org/wiki/NAACP",
    "wikidata_qid": "Q502044",
    "aliases": [
      "National Association for the Advancement of Colored People"
    ],
    "description": "civil rights organization in the United States",
    "description_wiki": "The National Association for the Advancement of Colored People (NAACP) is an American civil rights organization formed in 1909 as an interracial endeavor to advance justice for African Americans by a group including W. E. B. Du Bois, Mary White Ovington, Moorfield Storey, Ida B. Wells, Lillian Wald, Emil G. Hirsch and Henry Moskowitz."
  },
  {
    "id": 46,
    "entity": "H. M. Freeman",
    "type": "Person",
    "surface_forms": [
      "Dr. H. M. Freeman"
    ],
    "wikipedia_title": "H._M._Freeman",
    "wikipedia_url": "https://en.wikipedia.org/wiki/H._M._Freeman"
  },
  {
    "id": 47,
    "entity": "Larry Highfill",
    "type": "Person",
    "surface_forms": [
      "Larry Highfill"
    ],
    "wikipedia_title": "Larry_Highfill",
    "wikipedia_url": "https://en.wikipedia.org/wiki/Larry_Highfill"
  }
]