[
  {
    "id": 1,
    "entity": "Senator Cooper",
    "type": "Person",
    "surface_forms": [
      "Senator Cooper",
      "Cooper",
      "Senator Cooper said"
    ],
    "wikipedia_title": "Cooper (surname)",
    "wikipedia_url": "https://en.wikipedia.org/wiki/Cooper (surname)",
    "wikidata_qid": "Q1794217",
    "aliases": [
      "Cooper family name",
      "Cooper surname"
    ],
    "description": "family name",
    "description_wiki": "Cooper is a surname."
  },
  {
    "id": 2,
    "entity": "India",
    "type": "Place",
    "surface_forms": [
      "India"
    ],
    "wikipedia_title": "India",
    "wikipedia_url": "https://en.wikipedia.org/wiki/India",
    "wikidata_qid": "Q668",
    "aliases": [
      "Republic of India",
      "Bharat",
      "Bharatvarsh",
      "Hindustan",
      "Bharata",
      "Hindoostan",
      "Indostan",
      "Bharat Ganarajya",
      "Al Hind",
      "Tianzhu"
    ],
    "description": "country in South Asia",
    "description_wiki": "India, officially the Republic of India, is a country in South Asia."
  },
  {
    "id": 3,
    "entity": "East Germany",
    "type": "Place",
    "surface_forms": [
      "East Germany"
    ],
    "wikipedia_title": "East Germany",
    "wikipedia_url": "https://en.wikipedia.org/wiki/East Germany",
    "wikidata_qid": "Q16957",
    "aliases": [
      "GDR",
      "DDR",
      "Deutsche Demokratische Republik",
      "Communist Germany",
      "East Germany"
    ],
    "description": "1949–1990 country in central Europe, unified into modern Germany",
    "description_wiki": "East Germany, officially the German Democratic Republic (GDR), was a country in Central Europe from its formation on 7 October 1949 until its reunification with West Germany (Federal Republic of Germany) on 3 October 1990."
  },
  {
    "id": 4,
    "entity": "Louisville, Kentucky",
    "type": "Place",
    "surface_forms": [
      "Louisville",
      "Louisville, yeah",
      "I'm Lexington, so I don't know Louisville as well",
      "lives in Louisville"
    ],
    "wikipedia_title": "Louisville, Kentucky",
    "wikipedia_url": "https://en.wikipedia.org/wiki/Louisville, Kentucky",
    "wikidata_qid": "Q43668",
    "aliases": [
      "Louisville, Kentucky",
      "Louisville, KY",
      "Derby City",
      "Mouth of Beargrass",
      "Louisville, Jefferson County, Kentucky"
    ],
    "description": "county seat of Jefferson County, Kentucky, United States",
    "description_wiki": "Louisville is the most populous city in the U.S. state of Kentucky, sixth-most populous city in the Southeast, and the 27th-most-populous city in the United States."
  },
  {
    "id": 5,
    "entity": "Shamrock House",
    "type": "Organization",
    "surface_forms": [
      "the Shamrock House"
    ],
    "wikipedia_title": "Shamrock House",
    "wikipedia_url": "",
    "wikidata_qid": "Q26543054",
    "aliases": [],
    "description": "house in Brent Knoll, Sedgemoor, Somerset, England, UK",
    "description_wiki": ""
  },
  {
    "id": 6,
    "entity": "Bakery Square",
    "type": "Place",
    "surface_forms": [
      "Bakery Square"
    ],
    "wikipedia_title": "Bakery Square",
    "wikipedia_url": "https://en.wikipedia.org/wiki/Bakery Square",
    "wikidata_qid": "Q4849332",
    "aliases": [],
    "description": "shopping and office development in Pittsburgh's East End",
    "description_wiki": "Bakery Square is an open-air shopping and office development in the Pittsburgh neighborhood of Larimer, adjacent to the neighborhoods of Shadyside and East Liberty in the city's East End."
  },
  {
    "id": 7,
    "entity": "Church of the Advent (Louisville, Kentucky)",
    "type": "Place",
    "surface_forms": [
      "Church of the Advent on Baxter Avenue",
      "the Advent",
      "Advent"
    ],
    "wikipedia_title": "Church of the Advent (Louisville, Kentucky)",
    "wikipedia_url": "https://en.wikipedia.org/wiki/Church of the Advent (Louisville, Kentucky)"
  },
  {
    "id": 8,
    "entity": "Saint Thomas Episcopal Church (Louisville, Kentucky)",
    "type": "Place",
    "surface_forms": [
      "Saint Thomas",
      "Saint Thomas a member of the diocese"
    ],
    "wikipedia_title": "Saint Thomas Episcopal Church (Louisville, Kentucky)",
    "wikipedia_url": "https://en.wikipedia.org/wiki/Saint Thomas Episcopal Church (Louisville, Kentucky)"
  },
  {
    "id": 9,
    "entity": "Baxter Avenue",
    "type": "Place",
    "surface_forms": [
      "Baxter Avenue",
      "on Baxter"
    ],
    "wikipedia_title": "Baxter Avenue",
    "wikipedia_url": "",
    "wikidata_qid": "Q42658150",
    "aliases": [
      "Baxter Avenue Theatre"
    ],
    "description": "movie theater in Louisville, Kentucky, United States",
    "description_wiki": ""
  },
  {
    "id": 10,
    "entity": "Collegiate School (New York)",
    "type": "Organization",
    "surface_forms": [
      "Collegiate",
      "Collegiate School"
    ],
    "wikipedia_title": "Collegiate School (New York)",
    "wikipedia_url": "https://en.wikipedia.org/wiki/Collegiate School (New York)"
  },
  {
    "id": 11,
    "entity": "Brownborough Road",
    "type": "Place",
    "surface_forms": [
      "Brownborough Road"
    ],
    "wikipedia_title": "Brownborough Road",
    "wikipedia_url": "https://en.wikipedia.org/wiki/Brownborough Road"
  },
  {
    "id": 12,
    "entity": "John F. Kennedy",
    "type": "Person",
    "surface_forms": [
      "Kennedy"
    ],
    "wikipedia_title": "John F. Kennedy",
    "wikipedia_url": "https://en.wikipedia.org/wiki/John F. Kennedy",
    "wikidata_qid": "Q9696",
    "aliases": [
      "Kennedy",
      "Jack Kennedy",
      "President Kennedy",
      "John Fitzgerald Kennedy",
      "J. F. Kennedy",
      "JFK",
      "John Kennedy",
      "John Fitzgerald \"Jack\" Kennedy",
      "JF Kennedy",
      "John F Kennedy"
    ],
    "description": "president of the United States from 1961 to 1963 (1917–1963)",
    "description_wiki": "John Fitzgerald Kennedy (May 29, 1917 – November 22, 1963), also known as JFK, was the 35th president of the United States, serving from 1961 until his assassination in 1963."
  },
  {
    "id": 13,
    "entity": "Thruston Morton",
    "type": "Person",
    "surface_forms": [
      "Thruston Morton",
      "Morton",
      "Senator Morton",
      "Senator Morton Thruston Morton"
    ],
    "wikipedia_title": "Thruston Morton",
    "wikipedia_url": "https://en.wikipedia.org/wiki/Thruston Morton",
    "wikidata_qid": "Q2429723",
    "aliases": [],
    "description": "American politician (1907–1982)",
    "description_wiki": "Thruston Ballard Morton (August 19, 1907 – August 14, 1982) was an American politician."
  },
  {
    "id": 14,
    "entity": "Fred M. Vinson",
    "type": "Person",
    "surface_forms": [
      "Fred Vincent",
      "Fred Vincent, the Supreme Court Justice",
      "Fred Vincent, the Supreme Court Justice. Now he was Kentucky"
    ],
    "wikipedia_title": "Fred M. Vinson",
    "wikipedia_url": "https://en.wikipedia.org/wiki/Fred M. Vinson",
    "wikidata_qid": "Q460151",
    "aliases": [
      "Frederick Moore Vinson",
      "Fred Vinson"
    ],
    "description": "chief justice of the United States from 1946 to 1953",
    "description_wiki": "Frederick Moore Vinson (January 22, 1890 – September 8, 1953) was an American attorney and politician who served as the 13th chief justice of the United States from 1946 until his death in 1953."
  },
  {
    "id": 15,
    "entity": "Kentucky",
    "type": "Place",
    "surface_forms": [
      "Kentucky",
      "he was Kentucky"
    ],
    "wikipedia_title": "Kentucky",
    "wikipedia_url": "https://en.wikipedia.org/wiki/Kentucky",
    "wikidata_qid": "Q1603",
    "aliases": [
      "Commonwealth of Kentucky",
      "KY",
      "Kentucky, United States",
      "Bluegrass State",
      "Ky.",
      "US-KY"
    ],
    "description": "state of the United States of America",
    "description_wiki": "Kentucky (US:  , UK: ), officially the Commonwealth of Kentucky, is a landlocked state in the Southeastern region of the United States."
  },
  {
    "id": 16,
    "entity": "University of Louisville",
    "type": "Organization",
    "surface_forms": [
      "U of L",
      "U of L.",
      "University of Louisville"
    ],
    "wikipedia_title": "University of Louisville",
    "wikipedia_url": "https://en.wikipedia.org/wiki/University of Louisville",
    "wikidata_qid": "Q1317143",
    "aliases": [
      "UofL"
    ],
    "description": "public university in Kentucky",
    "description_wiki": "The University of Louisville (UofL) is a public research university in Louisville, Kentucky, United States."
  },
  {
    "id": 17,
    "entity": "Bennett College (New York)",
    "type": "Organization",
    "surface_forms": [
      "Bennett in Millbrook, New York",
      "Bennett"
    ],
    "wikipedia_title": "Bennett College (New York)",
    "wikipedia_url": "https://en.wikipedia.org/wiki/Bennett College (New York)",
    "wikidata_qid": "Q4889679",
    "aliases": [],
    "description": "former women's college in New York, USA",
    "description_wiki": "Bennett College was a women's college founded in 1890 and located in the village of Millbrook, New York."
  },
  {
    "id": 18,
    "entity": "Mount Vernon College for Women",
    "type": "Organization",
    "surface_forms": [
      "Mount Vernon"
    ],
    "wikipedia_title": "Mount Vernon College for Women",
    "wikipedia_url": "",
    "wikidata_qid": "Q6924363",
    "aliases": [
      "Mount Vernon College",
      "Mount Vernon Seminary and College"
    ],
    "description": "former private women's college in Washington, D.C, now part of George Washington University",
    "description_wiki": ""
  },
  {
    "id": 19,
    "entity": "Rose Blakely",
    "type": "Person",
    "surface_forms": [
      "Rose Blakely"
    ],
    "wikipedia_title": "Rose Blakely",
    "wikipedia_url": "https://en.wikipedia.org/wiki/Rose Blakely"
  },
  {
    "id": 20,
    "entity": "Betsy Johnson",
    "type": "Person",
    "surface_forms": [
      "Betsy Miguel",
      "Betsy Johnson"
    ],
    "wikipedia_title": "Betsy Johnson",
    "wikipedia_url": "https://en.wikipedia.org/wiki/Betsy Johnson",
    "wikidata_qid": "Q4898301",
    "aliases": [
      "Elizabeth Johnson",
      "Elizabeth \"Betsy\" Johnson",
      "Elizabeth Katharine Johnson",
      "Betsy Katharine Johnson"
    ],
    "description": "American politician",
    "description_wiki": "Elizabeth Katharine \"Betsy\" Johnson (born January 12, 1951) is an American aviator, entrepreneur, and politician who served in the Oregon House of Representatives from the 1st and 31st House districts from 2001 to 2005, and in the Oregon Senate from the 16th district from 2005 to 2021, as a member of the Democratic Party."
  },
  {
    "id": 21,
    "entity": "Washington, D.C.",
    "type": "Place",
    "surface_forms": [
      "Washington DC",
      "Washington, DC",
      "Washington State"
    ],
    "wikipedia_title": "Washington, D.C.",
    "wikipedia_url": "https://en.wikipedia.org/wiki/Washington, D.C.",
    "wikidata_qid": "Q61",
    "aliases": [
      "Washington, District of Columbia",
      "D.C. Washington",
      "The District",
      "District of Columbia",
      "City of Washington, D.C.",
      "Washington City, D.C.",
      "Nation's Capital (D.C.)",
      "Federal City (D.C.)",
      "Columbia District"
    ],
    "description": "capital city of the United States of America",
    "description_wiki": "Washington, D.C., officially the District of Columbia and commonly known as simply Washington or D.C., is the capital city and federal district of the United States."
  },
  {
    "id": 22,
    "entity": "Georgetown (Washington, D.C.)",
    "type": "Place",
    "surface_forms": [
      "Georgetown"
    ],
    "wikipedia_title": "Georgetown (Washington, D.C.)",
    "wikipedia_url": "https://en.wikipedia.org/wiki/Georgetown (Washington, D.C.)",
    "wikidata_qid": "Q1468648",
    "aliases": [
      "Georgetown Historic District",
      "Georgetown, Washington, D.C.",
      "George Town",
      "George-Town",
      "Town of George",
      "West Washington"
    ],
    "description": "neighborhood and historic district in Washington, D.C., United States",
    "description_wiki": "Georgetown is a historic neighborhood and commercial district in Northwest Washington, D.C., situated along the Potomac River."
  },
  {
    "id": 23,
    "entity": "Wisconsin Avenue",
    "type": "Place",
    "surface_forms": [
      "Wisconsin Avenue"
    ],
    "wikipedia_title": "Wisconsin Avenue",
    "wikipedia_url": "https://en.wikipedia.org/wiki/Wisconsin Avenue",
    "wikidata_qid": "Q4703783",
    "aliases": [
      "Wisconsin Ave",
      "Wisconsin Avenue NW",
      "Wisconsin Avenue N.W.",
      "Wisconsin Avenue, Maryland",
      "Wisconsin Ave NW",
      "High Street (Georgetown, Washington, D.C.)"
    ],
    "description": "major thoroughfare in Washington, D.C., and its Maryland suburbs, United States",
    "description_wiki": "Wisconsin Avenue is a major thoroughfare in the Washington metropolitan area."
  },
  {
    "id": 24,
    "entity": "Senate Agriculture Committee",
    "type": "Organization",
    "surface_forms": [
      "Agriculture Committee",
      "Senate Agriculture Committee"
    ],
    "wikipedia_title": "United States Senate Committee on Agriculture, Nutrition, and Forestry",
    "wikipedia_url": "https://en.wikipedia.org/wiki/United States Senate Committee on Agriculture, Nutrition, and Forestry",
    "wikidata_qid": "Q7891257",
    "aliases": [
      "Senate Agriculture, Nutrition, and Forestry Committee"
    ],
    "description": "standing committee of the United States Senate",
    "description_wiki": "The Committee on Agriculture, Nutrition, and Forestry is a committee of the United States Senate empowered with legislative oversight of all matters relating to the nation's agriculture industry, farming programs, forestry and logging, and legislation relating to nutrition, home economics, and rural development."
  },
  {
    "id": 25,
    "entity": "Senate Press Gallery",
    "type": "Organization",
    "surface_forms": [
      "Senate Press Gallery"
    ],
    "wikipedia_title": "Senate Press Gallery",
    "wikipedia_url": "https://en.wikipedia.org/wiki/Senate Press Gallery"
  },
  {
    "id": 26,
    "entity": "Frank Greer",
    "type": "Person",
    "surface_forms": [
      "Frank Greer"
    ],
    "wikipedia_title": "Frank Greer",
    "wikipedia_url": "https://en.wikipedia.org/wiki/Frank Greer",
    "wikidata_qid": "Q1802792",
    "aliases": [
      "Frank Bartholomew Greer"
    ],
    "description": "American rower (1879-1943)",
    "description_wiki": "Frank Bartholomew Greer (February 26, 1879 – May 7, 1943) was an American rower who competed in the 1904 Summer Olympics."
  },
  {
    "id": 27,
    "entity": "Old Senate Office Building",
    "type": "Place",
    "surface_forms": [
      "old Senate Office Building"
    ],
    "wikipedia_title": "Russell Senate Office Building",
    "wikipedia_url": "https://en.wikipedia.org/wiki/Russell Senate Office Building",
    "wikidata_qid": "Q2176952",
    "aliases": [],
    "description": "American government building",
    "description_wiki": "The Russell Senate Office Building is the oldest of the United States Senate office buildings."
  }
]